{
  "id": "e50ff97f-722e-46db-a57d-287d372fbc60",
  "prevId": "00000000-0000-0000-0000-000000000000",
  "version": "7",
  "dialect": "postgresql",
  "tables": {
    "public.accounts": {
      "name": "accounts",
      "schema": "",
      "columns": {
        "user_id": {
          "name": "user_id",
          "type": "uuid",
          "primaryKey": false,
          "notNull": true
        },
        "type": {
          "name": "type",
          "type": "text",
          "primaryKey": false,
          "notNull": true
        },
        "provider": {
          "name": "provider",
          "type": "text",
          "primaryKey": false,
          "notNull": true
        },
        "provider_account_id": {
          "name": "provider_account_id",
          "type": "text",
          "primaryKey": false,
          "notNull": true
        },
        "refresh_token": {
          "name": "refresh_token",
          "type": "text",
          "primaryKey": false,
          "notNull": false
        },
        "access_token": {
          "name": "access_token",
          "type": "text",
          "primaryKey": false,
          "notNull": false
        },
        "expires_at": {
          "name": "expires_at",
          "type": "integer",
          "primaryKey": false,
          "notNull": false
        },
        "token_type": {
          "name": "token_type",
          "type": "text",
          "primaryKey": false,
          "notNull": false
        },
        "scope": {
          "name": "scope",
          "type": "text",
          "primaryKey": false,
          "notNull": false
        },
        "id_token": {
          "name": "id_token",
          "type": "text",
          "primaryKey": false,
          "notNull": false
        },
        "session_state": {
          "name": "session_state",
          "type": "text",
          "primaryKey": false,
          "notNull": false
        }
      },
      "indexes": {},
      "foreignKeys": {
        "accounts_user_id_users_id_fk": {
          "name": "accounts_user_id_users_id_fk",
          "tableFrom": "accounts",
          "tableTo": "users",
          "columnsFrom": [
            "user_id"
          ],
          "columnsTo": [
            "id"
          ],
          "onDelete": "cascade",
          "onUpdate": "no action"
        }
      },
      "compositePrimaryKeys": {
        "accounts_provider_provider_account_id_pk": {
          "name": "accounts_provider_provider_account_id_pk",
          "columns": [
            "provider",
            "provider_account_id"
          ]
        }
      },
      "uniqueConstraints": {},
      "policies": {},
      "checkConstraints": {},
      "isRLSEnabled": false
    },
    "public.amenities": {
      "name": "amenities",
      "schema": "",
      "columns": {
        "id": {
          "name": "id",
          "type": "uuid",
          "primaryKey": true,
          "notNull": true,
          "default": "gen_random_uuid()"
        },
        "slug": {
          "name": "slug",
          "type": "text",
          "primaryKey": false,
          "notNull": true
        },
        "label": {
          "name": "label",
          "type": "text",
          "primaryKey": false,
          "notNull": true
        }
      },
      "indexes": {},
      "foreignKeys": {},
      "compositePrimaryKeys": {},
      "uniqueConstraints": {
        "amenities_slug_unique": {
          "name": "amenities_slug_unique",
          "nullsNotDistinct": false,
          "columns": [
            "slug"
          ]
        }
      },
      "policies": {},
      "checkConstraints": {},
      "isRLSEnabled": false
    },
    "public.assets": {
      "name": "assets",
      "schema": "",
      "columns": {
        "id": {
          "name": "id",
          "type": "uuid",
          "primaryKey": true,
          "notNull": true,
          "default": "gen_random_uuid()"
        },
        "building_id": {
          "name": "building_id",
          "type": "uuid",
          "primaryKey": false,
          "notNull": true
        },
        "kind": {
          "name": "kind",
          "type": "asset_kind",
          "typeSchema": "public",
          "primaryKey": false,
          "notNull": true
        },
        "storage_key": {
          "name": "storage_key",
          "type": "text",
          "primaryKey": false,
          "notNull": true
        },
        "source_url": {
          "name": "source_url",
          "type": "text",
          "primaryKey": false,
          "notNull": true
        },
        "license_basis": {
          "name": "license_basis",
          "type": "license_basis",
          "typeSchema": "public",
          "primaryKey": false,
          "notNull": true
        },
        "status": {
          "name": "status",
          "type": "asset_status",
          "typeSchema": "public",
          "primaryKey": false,
          "notNull": true,
          "default": "'needs_permission'"
        },
        "perceptual_hash": {
          "name": "perceptual_hash",
          "type": "text",
          "primaryKey": false,
          "notNull": false
        },
        "width": {
          "name": "width",
          "type": "integer",
          "primaryKey": false,
          "notNull": false
        },
        "height": {
          "name": "height",
          "type": "integer",
          "primaryKey": false,
          "notNull": false
        },
        "alt_text": {
          "name": "alt_text",
          "type": "text",
          "primaryKey": false,
          "notNull": true
        },
        "created_at": {
          "name": "created_at",
          "type": "timestamp with time zone",
          "primaryKey": false,
          "notNull": true,
          "default": "now()"
        }
      },
      "indexes": {
        "assets_building_kind_idx": {
          "name": "assets_building_kind_idx",
          "columns": [
            {
              "expression": "building_id",
              "isExpression": false,
              "asc": true,
              "nulls": "last"
            },
            {
              "expression": "kind",
              "isExpression": false,
              "asc": true,
              "nulls": "last"
            }
          ],
          "isUnique": false,
          "concurrently": false,
          "method": "btree",
          "with": {}
        }
      },
      "foreignKeys": {
        "assets_building_id_buildings_id_fk": {
          "name": "assets_building_id_buildings_id_fk",
          "tableFrom": "assets",
          "tableTo": "buildings",
          "columnsFrom": [
            "building_id"
          ],
          "columnsTo": [
            "id"
          ],
          "onDelete": "cascade",
          "onUpdate": "no action"
        }
      },
      "compositePrimaryKeys": {},
      "uniqueConstraints": {},
      "policies": {},
      "checkConstraints": {},
      "isRLSEnabled": false
    },
    "public.audit_log": {
      "name": "audit_log",
      "schema": "",
      "columns": {
        "id": {
          "name": "id",
          "type": "uuid",
          "primaryKey": true,
          "notNull": true,
          "default": "gen_random_uuid()"
        },
        "actor_id": {
          "name": "actor_id",
          "type": "uuid",
          "primaryKey": false,
          "notNull": false
        },
        "action": {
          "name": "action",
          "type": "text",
          "primaryKey": false,
          "notNull": true
        },
        "entity_type": {
          "name": "entity_type",
          "type": "text",
          "primaryKey": false,
          "notNull": true
        },
        "entity_id": {
          "name": "entity_id",
          "type": "uuid",
          "primaryKey": false,
          "notNull": true
        },
        "before": {
          "name": "before",
          "type": "jsonb",
          "primaryKey": false,
          "notNull": false
        },
        "after": {
          "name": "after",
          "type": "jsonb",
          "primaryKey": false,
          "notNull": false
        },
        "created_at": {
          "name": "created_at",
          "type": "timestamp with time zone",
          "primaryKey": false,
          "notNull": true,
          "default": "now()"
        }
      },
      "indexes": {
        "audit_log_entity_idx": {
          "name": "audit_log_entity_idx",
          "columns": [
            {
              "expression": "entity_type",
              "isExpression": false,
              "asc": true,
              "nulls": "last"
            },
            {
              "expression": "entity_id",
              "isExpression": false,
              "asc": true,
              "nulls": "last"
            },
            {
              "expression": "created_at",
              "isExpression": false,
              "asc": true,
              "nulls": "last"
            }
          ],
          "isUnique": false,
          "concurrently": false,
          "method": "btree",
          "with": {}
        }
      },
      "foreignKeys": {
        "audit_log_actor_id_users_id_fk": {
          "name": "audit_log_actor_id_users_id_fk",
          "tableFrom": "audit_log",
          "tableTo": "users",
          "columnsFrom": [
            "actor_id"
          ],
          "columnsTo": [
            "id"
          ],
          "onDelete": "no action",
          "onUpdate": "no action"
        }
      },
      "compositePrimaryKeys": {},
      "uniqueConstraints": {},
      "policies": {},
      "checkConstraints": {},
      "isRLSEnabled": false
    },
    "public.authenticators": {
      "name": "authenticators",
      "schema": "",
      "columns": {
        "credential_id": {
          "name": "credential_id",
          "type": "text",
          "primaryKey": false,
          "notNull": true
        },
        "user_id": {
          "name": "user_id",
          "type": "uuid",
          "primaryKey": false,
          "notNull": true
        },
        "provider_account_id": {
          "name": "provider_account_id",
          "type": "text",
          "primaryKey": false,
          "notNull": true
        },
        "credential_public_key": {
          "name": "credential_public_key",
          "type": "text",
          "primaryKey": false,
          "notNull": true
        },
        "counter": {
          "name": "counter",
          "type": "integer",
          "primaryKey": false,
          "notNull": true
        },
        "credential_device_type": {
          "name": "credential_device_type",
          "type": "text",
          "primaryKey": false,
          "notNull": true
        },
        "credential_backed_up": {
          "name": "credential_backed_up",
          "type": "boolean",
          "primaryKey": false,
          "notNull": true
        },
        "transports": {
          "name": "transports",
          "type": "text",
          "primaryKey": false,
          "notNull": false
        }
      },
      "indexes": {},
      "foreignKeys": {
        "authenticators_user_id_users_id_fk": {
          "name": "authenticators_user_id_users_id_fk",
          "tableFrom": "authenticators",
          "tableTo": "users",
          "columnsFrom": [
            "user_id"
          ],
          "columnsTo": [
            "id"
          ],
          "onDelete": "cascade",
          "onUpdate": "no action"
        }
      },
      "compositePrimaryKeys": {
        "authenticators_user_id_credential_id_pk": {
          "name": "authenticators_user_id_credential_id_pk",
          "columns": [
            "user_id",
            "credential_id"
          ]
        }
      },
      "uniqueConstraints": {
        "authenticators_credential_id_unique": {
          "name": "authenticators_credential_id_unique",
          "nullsNotDistinct": false,
          "columns": [
            "credential_id"
          ]
        }
      },
      "policies": {},
      "checkConstraints": {},
      "isRLSEnabled": false
    },
    "public.building_amenities": {
      "name": "building_amenities",
      "schema": "",
      "columns": {
        "building_id": {
          "name": "building_id",
          "type": "uuid",
          "primaryKey": false,
          "notNull": true
        },
        "amenity_id": {
          "name": "amenity_id",
          "type": "uuid",
          "primaryKey": false,
          "notNull": true
        }
      },
      "indexes": {},
      "foreignKeys": {
        "building_amenities_building_id_buildings_id_fk": {
          "name": "building_amenities_building_id_buildings_id_fk",
          "tableFrom": "building_amenities",
          "tableTo": "buildings",
          "columnsFrom": [
            "building_id"
          ],
          "columnsTo": [
            "id"
          ],
          "onDelete": "cascade",
          "onUpdate": "no action"
        },
        "building_amenities_amenity_id_amenities_id_fk": {
          "name": "building_amenities_amenity_id_amenities_id_fk",
          "tableFrom": "building_amenities",
          "tableTo": "amenities",
          "columnsFrom": [
            "amenity_id"
          ],
          "columnsTo": [
            "id"
          ],
          "onDelete": "cascade",
          "onUpdate": "no action"
        }
      },
      "compositePrimaryKeys": {
        "building_amenities_building_id_amenity_id_pk": {
          "name": "building_amenities_building_id_amenity_id_pk",
          "columns": [
            "building_id",
            "amenity_id"
          ]
        }
      },
      "uniqueConstraints": {},
      "policies": {},
      "checkConstraints": {},
      "isRLSEnabled": false
    },
    "public.building_links": {
      "name": "building_links",
      "schema": "",
      "columns": {
        "id": {
          "name": "id",
          "type": "uuid",
          "primaryKey": true,
          "notNull": true,
          "default": "gen_random_uuid()"
        },
        "building_id": {
          "name": "building_id",
          "type": "uuid",
          "primaryKey": false,
          "notNull": true
        },
        "kind": {
          "name": "kind",
          "type": "link_kind",
          "typeSchema": "public",
          "primaryKey": false,
          "notNull": true
        },
        "url": {
          "name": "url",
          "type": "text",
          "primaryKey": false,
          "notNull": true
        },
        "verification_status": {
          "name": "verification_status",
          "type": "verification_status",
          "typeSchema": "public",
          "primaryKey": false,
          "notNull": true,
          "default": "'unverified'"
        },
        "http_status": {
          "name": "http_status",
          "type": "integer",
          "primaryKey": false,
          "notNull": false
        },
        "last_checked_at": {
          "name": "last_checked_at",
          "type": "timestamp with time zone",
          "primaryKey": false,
          "notNull": false
        },
        "created_at": {
          "name": "created_at",
          "type": "timestamp with time zone",
          "primaryKey": false,
          "notNull": true,
          "default": "now()"
        }
      },
      "indexes": {
        "building_links_kind_url_uk": {
          "name": "building_links_kind_url_uk",
          "columns": [
            {
              "expression": "building_id",
              "isExpression": false,
              "asc": true,
              "nulls": "last"
            },
            {
              "expression": "kind",
              "isExpression": false,
              "asc": true,
              "nulls": "last"
            },
            {
              "expression": "url",
              "isExpression": false,
              "asc": true,
              "nulls": "last"
            }
          ],
          "isUnique": true,
          "concurrently": false,
          "method": "btree",
          "with": {}
        }
      },
      "foreignKeys": {
        "building_links_building_id_buildings_id_fk": {
          "name": "building_links_building_id_buildings_id_fk",
          "tableFrom": "building_links",
          "tableTo": "buildings",
          "columnsFrom": [
            "building_id"
          ],
          "columnsTo": [
            "id"
          ],
          "onDelete": "cascade",
          "onUpdate": "no action"
        }
      },
      "compositePrimaryKeys": {},
      "uniqueConstraints": {},
      "policies": {},
      "checkConstraints": {},
      "isRLSEnabled": false
    },
    "public.buildings": {
      "name": "buildings",
      "schema": "",
      "columns": {
        "id": {
          "name": "id",
          "type": "uuid",
          "primaryKey": true,
          "notNull": true,
          "default": "gen_random_uuid()"
        },
        "market_id": {
          "name": "market_id",
          "type": "uuid",
          "primaryKey": false,
          "notNull": true
        },
        "neighborhood_id": {
          "name": "neighborhood_id",
          "type": "uuid",
          "primaryKey": false,
          "notNull": false
        },
        "slug": {
          "name": "slug",
          "type": "text",
          "primaryKey": false,
          "notNull": true
        },
        "status": {
          "name": "status",
          "type": "building_status",
          "typeSchema": "public",
          "primaryKey": false,
          "notNull": true,
          "default": "'draft'"
        },
        "name": {
          "name": "name",
          "type": "text",
          "primaryKey": false,
          "notNull": true
        },
        "aka_names": {
          "name": "aka_names",
          "type": "text[]",
          "primaryKey": false,
          "notNull": true,
          "default": "'{}'"
        },
        "address_line1": {
          "name": "address_line1",
          "type": "text",
          "primaryKey": false,
          "notNull": true
        },
        "address_line2": {
          "name": "address_line2",
          "type": "text",
          "primaryKey": false,
          "notNull": false
        },
        "city": {
          "name": "city",
          "type": "text",
          "primaryKey": false,
          "notNull": true
        },
        "region": {
          "name": "region",
          "type": "text",
          "primaryKey": false,
          "notNull": true
        },
        "postal_code": {
          "name": "postal_code",
          "type": "text",
          "primaryKey": false,
          "notNull": true
        },
        "geom": {
          "name": "geom",
          "type": "geography(Point,4326)",
          "primaryKey": false,
          "notNull": false
        },
        "bbl": {
          "name": "bbl",
          "type": "text",
          "primaryKey": false,
          "notNull": false
        },
        "bin": {
          "name": "bin",
          "type": "text",
          "primaryKey": false,
          "notNull": false
        },
        "year_built": {
          "name": "year_built",
          "type": "integer",
          "primaryKey": false,
          "notNull": false
        },
        "floors": {
          "name": "floors",
          "type": "integer",
          "primaryKey": false,
          "notNull": false
        },
        "total_units": {
          "name": "total_units",
          "type": "integer",
          "primaryKey": false,
          "notNull": false
        },
        "developer": {
          "name": "developer",
          "type": "text",
          "primaryKey": false,
          "notNull": false
        },
        "property_manager": {
          "name": "property_manager",
          "type": "text",
          "primaryKey": false,
          "notNull": false
        },
        "leasing_platform": {
          "name": "leasing_platform",
          "type": "text",
          "primaryKey": false,
          "notNull": false
        },
        "pet_policy": {
          "name": "pet_policy",
          "type": "text",
          "primaryKey": false,
          "notNull": false
        },
        "fee_policy": {
          "name": "fee_policy",
          "type": "text",
          "primaryKey": false,
          "notNull": false
        },
        "verified_at": {
          "name": "verified_at",
          "type": "timestamp with time zone",
          "primaryKey": false,
          "notNull": false
        },
        "published_at": {
          "name": "published_at",
          "type": "timestamp with time zone",
          "primaryKey": false,
          "notNull": false
        },
        "created_at": {
          "name": "created_at",
          "type": "timestamp with time zone",
          "primaryKey": false,
          "notNull": true,
          "default": "now()"
        },
        "updated_at": {
          "name": "updated_at",
          "type": "timestamp with time zone",
          "primaryKey": false,
          "notNull": true,
          "default": "now()"
        }
      },
      "indexes": {
        "buildings_market_status_idx": {
          "name": "buildings_market_status_idx",
          "columns": [
            {
              "expression": "market_id",
              "isExpression": false,
              "asc": true,
              "nulls": "last"
            },
            {
              "expression": "status",
              "isExpression": false,
              "asc": true,
              "nulls": "last"
            }
          ],
          "isUnique": false,
          "concurrently": false,
          "method": "btree",
          "with": {}
        },
        "buildings_neighborhood_idx": {
          "name": "buildings_neighborhood_idx",
          "columns": [
            {
              "expression": "neighborhood_id",
              "isExpression": false,
              "asc": true,
              "nulls": "last"
            }
          ],
          "isUnique": false,
          "concurrently": false,
          "method": "btree",
          "with": {}
        },
        "buildings_bbl_uk": {
          "name": "buildings_bbl_uk",
          "columns": [
            {
              "expression": "bbl",
              "isExpression": false,
              "asc": true,
              "nulls": "last"
            }
          ],
          "isUnique": true,
          "concurrently": false,
          "method": "btree",
          "with": {}
        },
        "buildings_bin_uk": {
          "name": "buildings_bin_uk",
          "columns": [
            {
              "expression": "bin",
              "isExpression": false,
              "asc": true,
              "nulls": "last"
            }
          ],
          "isUnique": true,
          "concurrently": false,
          "method": "btree",
          "with": {}
        }
      },
      "foreignKeys": {
        "buildings_market_id_markets_id_fk": {
          "name": "buildings_market_id_markets_id_fk",
          "tableFrom": "buildings",
          "tableTo": "markets",
          "columnsFrom": [
            "market_id"
          ],
          "columnsTo": [
            "id"
          ],
          "onDelete": "no action",
          "onUpdate": "no action"
        },
        "buildings_neighborhood_id_neighborhoods_id_fk": {
          "name": "buildings_neighborhood_id_neighborhoods_id_fk",
          "tableFrom": "buildings",
          "tableTo": "neighborhoods",
          "columnsFrom": [
            "neighborhood_id"
          ],
          "columnsTo": [
            "id"
          ],
          "onDelete": "no action",
          "onUpdate": "no action"
        }
      },
      "compositePrimaryKeys": {},
      "uniqueConstraints": {
        "buildings_slug_unique": {
          "name": "buildings_slug_unique",
          "nullsNotDistinct": false,
          "columns": [
            "slug"
          ]
        }
      },
      "policies": {},
      "checkConstraints": {},
      "isRLSEnabled": false
    },
    "public.extraction_jobs": {
      "name": "extraction_jobs",
      "schema": "",
      "columns": {
        "id": {
          "name": "id",
          "type": "uuid",
          "primaryKey": true,
          "notNull": true,
          "default": "gen_random_uuid()"
        },
        "submission_id": {
          "name": "submission_id",
          "type": "uuid",
          "primaryKey": false,
          "notNull": false
        },
        "submitted_url": {
          "name": "submitted_url",
          "type": "text",
          "primaryKey": false,
          "notNull": true
        },
        "normalized_url": {
          "name": "normalized_url",
          "type": "text",
          "primaryKey": false,
          "notNull": true
        },
        "stage": {
          "name": "stage",
          "type": "job_stage",
          "typeSchema": "public",
          "primaryKey": false,
          "notNull": true,
          "default": "'intake'"
        },
        "status": {
          "name": "status",
          "type": "job_status",
          "typeSchema": "public",
          "primaryKey": false,
          "notNull": true,
          "default": "'queued'"
        },
        "attempt_count": {
          "name": "attempt_count",
          "type": "integer",
          "primaryKey": false,
          "notNull": true,
          "default": 0
        },
        "cost_micros": {
          "name": "cost_micros",
          "type": "integer",
          "primaryKey": false,
          "notNull": true,
          "default": 0
        },
        "errors": {
          "name": "errors",
          "type": "jsonb",
          "primaryKey": false,
          "notNull": true,
          "default": "'[]'::jsonb"
        },
        "timings": {
          "name": "timings",
          "type": "jsonb",
          "primaryKey": false,
          "notNull": true,
          "default": "'{}'::jsonb"
        },
        "next_attempt_at": {
          "name": "next_attempt_at",
          "type": "timestamp with time zone",
          "primaryKey": false,
          "notNull": false
        },
        "created_at": {
          "name": "created_at",
          "type": "timestamp with time zone",
          "primaryKey": false,
          "notNull": true,
          "default": "now()"
        },
        "updated_at": {
          "name": "updated_at",
          "type": "timestamp with time zone",
          "primaryKey": false,
          "notNull": true,
          "default": "now()"
        }
      },
      "indexes": {
        "extraction_jobs_status_idx": {
          "name": "extraction_jobs_status_idx",
          "columns": [
            {
              "expression": "status",
              "isExpression": false,
              "asc": true,
              "nulls": "last"
            },
            {
              "expression": "next_attempt_at",
              "isExpression": false,
              "asc": true,
              "nulls": "last"
            }
          ],
          "isUnique": false,
          "concurrently": false,
          "method": "btree",
          "with": {}
        }
      },
      "foreignKeys": {
        "extraction_jobs_submission_id_submissions_id_fk": {
          "name": "extraction_jobs_submission_id_submissions_id_fk",
          "tableFrom": "extraction_jobs",
          "tableTo": "submissions",
          "columnsFrom": [
            "submission_id"
          ],
          "columnsTo": [
            "id"
          ],
          "onDelete": "no action",
          "onUpdate": "no action"
        }
      },
      "compositePrimaryKeys": {},
      "uniqueConstraints": {},
      "policies": {},
      "checkConstraints": {},
      "isRLSEnabled": false
    },
    "public.field_provenance": {
      "name": "field_provenance",
      "schema": "",
      "columns": {
        "id": {
          "name": "id",
          "type": "uuid",
          "primaryKey": true,
          "notNull": true,
          "default": "gen_random_uuid()"
        },
        "building_id": {
          "name": "building_id",
          "type": "uuid",
          "primaryKey": false,
          "notNull": true
        },
        "source_id": {
          "name": "source_id",
          "type": "uuid",
          "primaryKey": false,
          "notNull": true
        },
        "field_path": {
          "name": "field_path",
          "type": "text",
          "primaryKey": false,
          "notNull": true
        },
        "value": {
          "name": "value",
          "type": "jsonb",
          "primaryKey": false,
          "notNull": true
        },
        "confidence": {
          "name": "confidence",
          "type": "numeric(4, 3)",
          "primaryKey": false,
          "notNull": true
        },
        "supporting_snippet": {
          "name": "supporting_snippet",
          "type": "text",
          "primaryKey": false,
          "notNull": false
        },
        "reviewed_by": {
          "name": "reviewed_by",
          "type": "uuid",
          "primaryKey": false,
          "notNull": false
        },
        "reviewed_at": {
          "name": "reviewed_at",
          "type": "timestamp with time zone",
          "primaryKey": false,
          "notNull": false
        },
        "created_at": {
          "name": "created_at",
          "type": "timestamp with time zone",
          "primaryKey": false,
          "notNull": true,
          "default": "now()"
        }
      },
      "indexes": {
        "field_provenance_building_path_idx": {
          "name": "field_provenance_building_path_idx",
          "columns": [
            {
              "expression": "building_id",
              "isExpression": false,
              "asc": true,
              "nulls": "last"
            },
            {
              "expression": "field_path",
              "isExpression": false,
              "asc": true,
              "nulls": "last"
            }
          ],
          "isUnique": false,
          "concurrently": false,
          "method": "btree",
          "with": {}
        },
        "field_provenance_source_idx": {
          "name": "field_provenance_source_idx",
          "columns": [
            {
              "expression": "source_id",
              "isExpression": false,
              "asc": true,
              "nulls": "last"
            }
          ],
          "isUnique": false,
          "concurrently": false,
          "method": "btree",
          "with": {}
        }
      },
      "foreignKeys": {
        "field_provenance_building_id_buildings_id_fk": {
          "name": "field_provenance_building_id_buildings_id_fk",
          "tableFrom": "field_provenance",
          "tableTo": "buildings",
          "columnsFrom": [
            "building_id"
          ],
          "columnsTo": [
            "id"
          ],
          "onDelete": "cascade",
          "onUpdate": "no action"
        },
        "field_provenance_source_id_sources_id_fk": {
          "name": "field_provenance_source_id_sources_id_fk",
          "tableFrom": "field_provenance",
          "tableTo": "sources",
          "columnsFrom": [
            "source_id"
          ],
          "columnsTo": [
            "id"
          ],
          "onDelete": "no action",
          "onUpdate": "no action"
        },
        "field_provenance_reviewed_by_users_id_fk": {
          "name": "field_provenance_reviewed_by_users_id_fk",
          "tableFrom": "field_provenance",
          "tableTo": "users",
          "columnsFrom": [
            "reviewed_by"
          ],
          "columnsTo": [
            "id"
          ],
          "onDelete": "no action",
          "onUpdate": "no action"
        }
      },
      "compositePrimaryKeys": {},
      "uniqueConstraints": {},
      "policies": {},
      "checkConstraints": {},
      "isRLSEnabled": false
    },
    "public.floor_plans": {
      "name": "floor_plans",
      "schema": "",
      "columns": {
        "id": {
          "name": "id",
          "type": "uuid",
          "primaryKey": true,
          "notNull": true,
          "default": "gen_random_uuid()"
        },
        "building_id": {
          "name": "building_id",
          "type": "uuid",
          "primaryKey": false,
          "notNull": true
        },
        "source_id": {
          "name": "source_id",
          "type": "uuid",
          "primaryKey": false,
          "notNull": true
        },
        "asset_id": {
          "name": "asset_id",
          "type": "uuid",
          "primaryKey": false,
          "notNull": false
        },
        "label": {
          "name": "label",
          "type": "text",
          "primaryKey": false,
          "notNull": true
        },
        "beds": {
          "name": "beds",
          "type": "numeric(3, 1)",
          "primaryKey": false,
          "notNull": false
        },
        "baths": {
          "name": "baths",
          "type": "numeric(3, 1)",
          "primaryKey": false,
          "notNull": false
        },
        "sqft": {
          "name": "sqft",
          "type": "integer",
          "primaryKey": false,
          "notNull": false
        },
        "type": {
          "name": "type",
          "type": "floor_plan_type",
          "typeSchema": "public",
          "primaryKey": false,
          "notNull": true
        },
        "embed_url": {
          "name": "embed_url",
          "type": "text",
          "primaryKey": false,
          "notNull": false
        },
        "license_basis": {
          "name": "license_basis",
          "type": "license_basis",
          "typeSchema": "public",
          "primaryKey": false,
          "notNull": true
        },
        "created_at": {
          "name": "created_at",
          "type": "timestamp with time zone",
          "primaryKey": false,
          "notNull": true,
          "default": "now()"
        }
      },
      "indexes": {
        "floor_plans_building_idx": {
          "name": "floor_plans_building_idx",
          "columns": [
            {
              "expression": "building_id",
              "isExpression": false,
              "asc": true,
              "nulls": "last"
            }
          ],
          "isUnique": false,
          "concurrently": false,
          "method": "btree",
          "with": {}
        }
      },
      "foreignKeys": {
        "floor_plans_building_id_buildings_id_fk": {
          "name": "floor_plans_building_id_buildings_id_fk",
          "tableFrom": "floor_plans",
          "tableTo": "buildings",
          "columnsFrom": [
            "building_id"
          ],
          "columnsTo": [
            "id"
          ],
          "onDelete": "cascade",
          "onUpdate": "no action"
        },
        "floor_plans_source_id_sources_id_fk": {
          "name": "floor_plans_source_id_sources_id_fk",
          "tableFrom": "floor_plans",
          "tableTo": "sources",
          "columnsFrom": [
            "source_id"
          ],
          "columnsTo": [
            "id"
          ],
          "onDelete": "no action",
          "onUpdate": "no action"
        },
        "floor_plans_asset_id_assets_id_fk": {
          "name": "floor_plans_asset_id_assets_id_fk",
          "tableFrom": "floor_plans",
          "tableTo": "assets",
          "columnsFrom": [
            "asset_id"
          ],
          "columnsTo": [
            "id"
          ],
          "onDelete": "no action",
          "onUpdate": "no action"
        }
      },
      "compositePrimaryKeys": {},
      "uniqueConstraints": {},
      "policies": {},
      "checkConstraints": {},
      "isRLSEnabled": false
    },
    "public.markets": {
      "name": "markets",
      "schema": "",
      "columns": {
        "id": {
          "name": "id",
          "type": "uuid",
          "primaryKey": true,
          "notNull": true,
          "default": "gen_random_uuid()"
        },
        "slug": {
          "name": "slug",
          "type": "text",
          "primaryKey": false,
          "notNull": true
        },
        "name": {
          "name": "name",
          "type": "text",
          "primaryKey": false,
          "notNull": true
        },
        "boundary": {
          "name": "boundary",
          "type": "geography(MultiPolygon,4326)",
          "primaryKey": false,
          "notNull": false
        },
        "active": {
          "name": "active",
          "type": "boolean",
          "primaryKey": false,
          "notNull": true,
          "default": true
        },
        "created_at": {
          "name": "created_at",
          "type": "timestamp with time zone",
          "primaryKey": false,
          "notNull": true,
          "default": "now()"
        }
      },
      "indexes": {},
      "foreignKeys": {},
      "compositePrimaryKeys": {},
      "uniqueConstraints": {
        "markets_slug_unique": {
          "name": "markets_slug_unique",
          "nullsNotDistinct": false,
          "columns": [
            "slug"
          ]
        }
      },
      "policies": {},
      "checkConstraints": {},
      "isRLSEnabled": false
    },
    "public.mfa_credentials": {
      "name": "mfa_credentials",
      "schema": "",
      "columns": {
        "id": {
          "name": "id",
          "type": "uuid",
          "primaryKey": true,
          "notNull": true,
          "default": "gen_random_uuid()"
        },
        "user_id": {
          "name": "user_id",
          "type": "uuid",
          "primaryKey": false,
          "notNull": true
        },
        "encrypted_secret": {
          "name": "encrypted_secret",
          "type": "text",
          "primaryKey": false,
          "notNull": true
        },
        "enabled_at": {
          "name": "enabled_at",
          "type": "timestamp with time zone",
          "primaryKey": false,
          "notNull": false
        },
        "created_at": {
          "name": "created_at",
          "type": "timestamp with time zone",
          "primaryKey": false,
          "notNull": true,
          "default": "now()"
        }
      },
      "indexes": {},
      "foreignKeys": {
        "mfa_credentials_user_id_users_id_fk": {
          "name": "mfa_credentials_user_id_users_id_fk",
          "tableFrom": "mfa_credentials",
          "tableTo": "users",
          "columnsFrom": [
            "user_id"
          ],
          "columnsTo": [
            "id"
          ],
          "onDelete": "cascade",
          "onUpdate": "no action"
        }
      },
      "compositePrimaryKeys": {},
      "uniqueConstraints": {
        "mfa_credentials_user_id_unique": {
          "name": "mfa_credentials_user_id_unique",
          "nullsNotDistinct": false,
          "columns": [
            "user_id"
          ]
        }
      },
      "policies": {},
      "checkConstraints": {},
      "isRLSEnabled": false
    },
    "public.neighborhoods": {
      "name": "neighborhoods",
      "schema": "",
      "columns": {
        "id": {
          "name": "id",
          "type": "uuid",
          "primaryKey": true,
          "notNull": true,
          "default": "gen_random_uuid()"
        },
        "market_id": {
          "name": "market_id",
          "type": "uuid",
          "primaryKey": false,
          "notNull": true
        },
        "slug": {
          "name": "slug",
          "type": "text",
          "primaryKey": false,
          "notNull": true
        },
        "name": {
          "name": "name",
          "type": "text",
          "primaryKey": false,
          "notNull": true
        },
        "boundary": {
          "name": "boundary",
          "type": "geography(MultiPolygon,4326)",
          "primaryKey": false,
          "notNull": false
        },
        "created_at": {
          "name": "created_at",
          "type": "timestamp with time zone",
          "primaryKey": false,
          "notNull": true,
          "default": "now()"
        }
      },
      "indexes": {
        "neighborhood_market_slug_uk": {
          "name": "neighborhood_market_slug_uk",
          "columns": [
            {
              "expression": "market_id",
              "isExpression": false,
              "asc": true,
              "nulls": "last"
            },
            {
              "expression": "slug",
              "isExpression": false,
              "asc": true,
              "nulls": "last"
            }
          ],
          "isUnique": true,
          "concurrently": false,
          "method": "btree",
          "with": {}
        }
      },
      "foreignKeys": {
        "neighborhoods_market_id_markets_id_fk": {
          "name": "neighborhoods_market_id_markets_id_fk",
          "tableFrom": "neighborhoods",
          "tableTo": "markets",
          "columnsFrom": [
            "market_id"
          ],
          "columnsTo": [
            "id"
          ],
          "onDelete": "no action",
          "onUpdate": "no action"
        }
      },
      "compositePrimaryKeys": {},
      "uniqueConstraints": {},
      "policies": {},
      "checkConstraints": {},
      "isRLSEnabled": false
    },
    "public.recovery_codes": {
      "name": "recovery_codes",
      "schema": "",
      "columns": {
        "id": {
          "name": "id",
          "type": "uuid",
          "primaryKey": true,
          "notNull": true,
          "default": "gen_random_uuid()"
        },
        "user_id": {
          "name": "user_id",
          "type": "uuid",
          "primaryKey": false,
          "notNull": true
        },
        "code_hash": {
          "name": "code_hash",
          "type": "text",
          "primaryKey": false,
          "notNull": true
        },
        "used_at": {
          "name": "used_at",
          "type": "timestamp with time zone",
          "primaryKey": false,
          "notNull": false
        },
        "created_at": {
          "name": "created_at",
          "type": "timestamp with time zone",
          "primaryKey": false,
          "notNull": true,
          "default": "now()"
        }
      },
      "indexes": {
        "recovery_codes_user_idx": {
          "name": "recovery_codes_user_idx",
          "columns": [
            {
              "expression": "user_id",
              "isExpression": false,
              "asc": true,
              "nulls": "last"
            }
          ],
          "isUnique": false,
          "concurrently": false,
          "method": "btree",
          "with": {}
        }
      },
      "foreignKeys": {
        "recovery_codes_user_id_users_id_fk": {
          "name": "recovery_codes_user_id_users_id_fk",
          "tableFrom": "recovery_codes",
          "tableTo": "users",
          "columnsFrom": [
            "user_id"
          ],
          "columnsTo": [
            "id"
          ],
          "onDelete": "cascade",
          "onUpdate": "no action"
        }
      },
      "compositePrimaryKeys": {},
      "uniqueConstraints": {},
      "policies": {},
      "checkConstraints": {},
      "isRLSEnabled": false
    },
    "public.review_items": {
      "name": "review_items",
      "schema": "",
      "columns": {
        "id": {
          "name": "id",
          "type": "uuid",
          "primaryKey": true,
          "notNull": true,
          "default": "gen_random_uuid()"
        },
        "extraction_job_id": {
          "name": "extraction_job_id",
          "type": "uuid",
          "primaryKey": false,
          "notNull": false
        },
        "building_id": {
          "name": "building_id",
          "type": "uuid",
          "primaryKey": false,
          "notNull": false
        },
        "assignee_id": {
          "name": "assignee_id",
          "type": "uuid",
          "primaryKey": false,
          "notNull": false
        },
        "type": {
          "name": "type",
          "type": "review_type",
          "typeSchema": "public",
          "primaryKey": false,
          "notNull": true
        },
        "status": {
          "name": "status",
          "type": "review_status",
          "typeSchema": "public",
          "primaryKey": false,
          "notNull": true,
          "default": "'open'"
        },
        "payload_diff": {
          "name": "payload_diff",
          "type": "jsonb",
          "primaryKey": false,
          "notNull": true
        },
        "decisions": {
          "name": "decisions",
          "type": "jsonb",
          "primaryKey": false,
          "notNull": true,
          "default": "'{}'::jsonb"
        },
        "due_at": {
          "name": "due_at",
          "type": "timestamp with time zone",
          "primaryKey": false,
          "notNull": false
        },
        "created_at": {
          "name": "created_at",
          "type": "timestamp with time zone",
          "primaryKey": false,
          "notNull": true,
          "default": "now()"
        },
        "updated_at": {
          "name": "updated_at",
          "type": "timestamp with time zone",
          "primaryKey": false,
          "notNull": true,
          "default": "now()"
        }
      },
      "indexes": {
        "review_items_queue_idx": {
          "name": "review_items_queue_idx",
          "columns": [
            {
              "expression": "status",
              "isExpression": false,
              "asc": true,
              "nulls": "last"
            },
            {
              "expression": "due_at",
              "isExpression": false,
              "asc": true,
              "nulls": "last"
            }
          ],
          "isUnique": false,
          "concurrently": false,
          "method": "btree",
          "with": {}
        }
      },
      "foreignKeys": {
        "review_items_extraction_job_id_extraction_jobs_id_fk": {
          "name": "review_items_extraction_job_id_extraction_jobs_id_fk",
          "tableFrom": "review_items",
          "tableTo": "extraction_jobs",
          "columnsFrom": [
            "extraction_job_id"
          ],
          "columnsTo": [
            "id"
          ],
          "onDelete": "no action",
          "onUpdate": "no action"
        },
        "review_items_building_id_buildings_id_fk": {
          "name": "review_items_building_id_buildings_id_fk",
          "tableFrom": "review_items",
          "tableTo": "buildings",
          "columnsFrom": [
            "building_id"
          ],
          "columnsTo": [
            "id"
          ],
          "onDelete": "no action",
          "onUpdate": "no action"
        },
        "review_items_assignee_id_users_id_fk": {
          "name": "review_items_assignee_id_users_id_fk",
          "tableFrom": "review_items",
          "tableTo": "users",
          "columnsFrom": [
            "assignee_id"
          ],
          "columnsTo": [
            "id"
          ],
          "onDelete": "no action",
          "onUpdate": "no action"
        }
      },
      "compositePrimaryKeys": {},
      "uniqueConstraints": {},
      "policies": {},
      "checkConstraints": {},
      "isRLSEnabled": false
    },
    "public.sessions": {
      "name": "sessions",
      "schema": "",
      "columns": {
        "session_token": {
          "name": "session_token",
          "type": "text",
          "primaryKey": true,
          "notNull": true
        },
        "user_id": {
          "name": "user_id",
          "type": "uuid",
          "primaryKey": false,
          "notNull": true
        },
        "expires": {
          "name": "expires",
          "type": "timestamp with time zone",
          "primaryKey": false,
          "notNull": true
        }
      },
      "indexes": {},
      "foreignKeys": {
        "sessions_user_id_users_id_fk": {
          "name": "sessions_user_id_users_id_fk",
          "tableFrom": "sessions",
          "tableTo": "users",
          "columnsFrom": [
            "user_id"
          ],
          "columnsTo": [
            "id"
          ],
          "onDelete": "cascade",
          "onUpdate": "no action"
        }
      },
      "compositePrimaryKeys": {},
      "uniqueConstraints": {},
      "policies": {},
      "checkConstraints": {},
      "isRLSEnabled": false
    },
    "public.sources": {
      "name": "sources",
      "schema": "",
      "columns": {
        "id": {
          "name": "id",
          "type": "uuid",
          "primaryKey": true,
          "notNull": true,
          "default": "gen_random_uuid()"
        },
        "extraction_job_id": {
          "name": "extraction_job_id",
          "type": "uuid",
          "primaryKey": false,
          "notNull": false
        },
        "url": {
          "name": "url",
          "type": "text",
          "primaryKey": false,
          "notNull": true
        },
        "fetched_at": {
          "name": "fetched_at",
          "type": "timestamp with time zone",
          "primaryKey": false,
          "notNull": true
        },
        "snapshot_key": {
          "name": "snapshot_key",
          "type": "text",
          "primaryKey": false,
          "notNull": false
        },
        "content_hash": {
          "name": "content_hash",
          "type": "text",
          "primaryKey": false,
          "notNull": false
        },
        "robots_allowed": {
          "name": "robots_allowed",
          "type": "boolean",
          "primaryKey": false,
          "notNull": true
        },
        "created_at": {
          "name": "created_at",
          "type": "timestamp with time zone",
          "primaryKey": false,
          "notNull": true,
          "default": "now()"
        }
      },
      "indexes": {
        "sources_job_idx": {
          "name": "sources_job_idx",
          "columns": [
            {
              "expression": "extraction_job_id",
              "isExpression": false,
              "asc": true,
              "nulls": "last"
            }
          ],
          "isUnique": false,
          "concurrently": false,
          "method": "btree",
          "with": {}
        }
      },
      "foreignKeys": {
        "sources_extraction_job_id_extraction_jobs_id_fk": {
          "name": "sources_extraction_job_id_extraction_jobs_id_fk",
          "tableFrom": "sources",
          "tableTo": "extraction_jobs",
          "columnsFrom": [
            "extraction_job_id"
          ],
          "columnsTo": [
            "id"
          ],
          "onDelete": "no action",
          "onUpdate": "no action"
        }
      },
      "compositePrimaryKeys": {},
      "uniqueConstraints": {},
      "policies": {},
      "checkConstraints": {},
      "isRLSEnabled": false
    },
    "public.sourcing_tasks": {
      "name": "sourcing_tasks",
      "schema": "",
      "columns": {
        "id": {
          "name": "id",
          "type": "uuid",
          "primaryKey": true,
          "notNull": true,
          "default": "gen_random_uuid()"
        },
        "building_id": {
          "name": "building_id",
          "type": "uuid",
          "primaryKey": false,
          "notNull": true
        },
        "assignee_id": {
          "name": "assignee_id",
          "type": "uuid",
          "primaryKey": false,
          "notNull": false
        },
        "kind": {
          "name": "kind",
          "type": "task_kind",
          "typeSchema": "public",
          "primaryKey": false,
          "notNull": true
        },
        "status": {
          "name": "status",
          "type": "task_status",
          "typeSchema": "public",
          "primaryKey": false,
          "notNull": true,
          "default": "'backlog'"
        },
        "urls_checked": {
          "name": "urls_checked",
          "type": "text[]",
          "primaryKey": false,
          "notNull": true,
          "default": "'{}'"
        },
        "notes": {
          "name": "notes",
          "type": "text",
          "primaryKey": false,
          "notNull": false
        },
        "due_at": {
          "name": "due_at",
          "type": "timestamp with time zone",
          "primaryKey": false,
          "notNull": false
        },
        "created_at": {
          "name": "created_at",
          "type": "timestamp with time zone",
          "primaryKey": false,
          "notNull": true,
          "default": "now()"
        },
        "updated_at": {
          "name": "updated_at",
          "type": "timestamp with time zone",
          "primaryKey": false,
          "notNull": true,
          "default": "now()"
        }
      },
      "indexes": {
        "sourcing_tasks_status_idx": {
          "name": "sourcing_tasks_status_idx",
          "columns": [
            {
              "expression": "status",
              "isExpression": false,
              "asc": true,
              "nulls": "last"
            },
            {
              "expression": "due_at",
              "isExpression": false,
              "asc": true,
              "nulls": "last"
            }
          ],
          "isUnique": false,
          "concurrently": false,
          "method": "btree",
          "with": {}
        }
      },
      "foreignKeys": {
        "sourcing_tasks_building_id_buildings_id_fk": {
          "name": "sourcing_tasks_building_id_buildings_id_fk",
          "tableFrom": "sourcing_tasks",
          "tableTo": "buildings",
          "columnsFrom": [
            "building_id"
          ],
          "columnsTo": [
            "id"
          ],
          "onDelete": "cascade",
          "onUpdate": "no action"
        },
        "sourcing_tasks_assignee_id_users_id_fk": {
          "name": "sourcing_tasks_assignee_id_users_id_fk",
          "tableFrom": "sourcing_tasks",
          "tableTo": "users",
          "columnsFrom": [
            "assignee_id"
          ],
          "columnsTo": [
            "id"
          ],
          "onDelete": "no action",
          "onUpdate": "no action"
        }
      },
      "compositePrimaryKeys": {},
      "uniqueConstraints": {},
      "policies": {},
      "checkConstraints": {},
      "isRLSEnabled": false
    },
    "public.submissions": {
      "name": "submissions",
      "schema": "",
      "columns": {
        "id": {
          "name": "id",
          "type": "uuid",
          "primaryKey": true,
          "notNull": true,
          "default": "gen_random_uuid()"
        },
        "submitted_url": {
          "name": "submitted_url",
          "type": "text",
          "primaryKey": false,
          "notNull": true
        },
        "optional_name": {
          "name": "optional_name",
          "type": "text",
          "primaryKey": false,
          "notNull": false
        },
        "optional_address": {
          "name": "optional_address",
          "type": "text",
          "primaryKey": false,
          "notNull": false
        },
        "contact_email": {
          "name": "contact_email",
          "type": "text",
          "primaryKey": false,
          "notNull": false
        },
        "status": {
          "name": "status",
          "type": "submission_status",
          "typeSchema": "public",
          "primaryKey": false,
          "notNull": true,
          "default": "'received'"
        },
        "created_at": {
          "name": "created_at",
          "type": "timestamp with time zone",
          "primaryKey": false,
          "notNull": true,
          "default": "now()"
        }
      },
      "indexes": {},
      "foreignKeys": {},
      "compositePrimaryKeys": {},
      "uniqueConstraints": {},
      "policies": {},
      "checkConstraints": {},
      "isRLSEnabled": false
    },
    "public.unit_mix": {
      "name": "unit_mix",
      "schema": "",
      "columns": {
        "id": {
          "name": "id",
          "type": "uuid",
          "primaryKey": true,
          "notNull": true,
          "default": "gen_random_uuid()"
        },
        "building_id": {
          "name": "building_id",
          "type": "uuid",
          "primaryKey": false,
          "notNull": true
        },
        "source_id": {
          "name": "source_id",
          "type": "uuid",
          "primaryKey": false,
          "notNull": true
        },
        "bed_count": {
          "name": "bed_count",
          "type": "numeric(3, 1)",
          "primaryKey": false,
          "notNull": true
        },
        "bath_count": {
          "name": "bath_count",
          "type": "numeric(3, 1)",
          "primaryKey": false,
          "notNull": false
        },
        "unit_count": {
          "name": "unit_count",
          "type": "integer",
          "primaryKey": false,
          "notNull": false
        },
        "rent_min": {
          "name": "rent_min",
          "type": "integer",
          "primaryKey": false,
          "notNull": false
        },
        "rent_max": {
          "name": "rent_max",
          "type": "integer",
          "primaryKey": false,
          "notNull": false
        },
        "sqft_min": {
          "name": "sqft_min",
          "type": "integer",
          "primaryKey": false,
          "notNull": false
        },
        "sqft_max": {
          "name": "sqft_max",
          "type": "integer",
          "primaryKey": false,
          "notNull": false
        },
        "as_of_date": {
          "name": "as_of_date",
          "type": "date",
          "primaryKey": false,
          "notNull": true
        },
        "confidence": {
          "name": "confidence",
          "type": "numeric(4, 3)",
          "primaryKey": false,
          "notNull": true
        },
        "reviewed_by": {
          "name": "reviewed_by",
          "type": "uuid",
          "primaryKey": false,
          "notNull": false
        },
        "reviewed_at": {
          "name": "reviewed_at",
          "type": "timestamp with time zone",
          "primaryKey": false,
          "notNull": false
        }
      },
      "indexes": {
        "unit_mix_building_idx": {
          "name": "unit_mix_building_idx",
          "columns": [
            {
              "expression": "building_id",
              "isExpression": false,
              "asc": true,
              "nulls": "last"
            }
          ],
          "isUnique": false,
          "concurrently": false,
          "method": "btree",
          "with": {}
        }
      },
      "foreignKeys": {
        "unit_mix_building_id_buildings_id_fk": {
          "name": "unit_mix_building_id_buildings_id_fk",
          "tableFrom": "unit_mix",
          "tableTo": "buildings",
          "columnsFrom": [
            "building_id"
          ],
          "columnsTo": [
            "id"
          ],
          "onDelete": "cascade",
          "onUpdate": "no action"
        },
        "unit_mix_source_id_sources_id_fk": {
          "name": "unit_mix_source_id_sources_id_fk",
          "tableFrom": "unit_mix",
          "tableTo": "sources",
          "columnsFrom": [
            "source_id"
          ],
          "columnsTo": [
            "id"
          ],
          "onDelete": "no action",
          "onUpdate": "no action"
        },
        "unit_mix_reviewed_by_users_id_fk": {
          "name": "unit_mix_reviewed_by_users_id_fk",
          "tableFrom": "unit_mix",
          "tableTo": "users",
          "columnsFrom": [
            "reviewed_by"
          ],
          "columnsTo": [
            "id"
          ],
          "onDelete": "no action",
          "onUpdate": "no action"
        }
      },
      "compositePrimaryKeys": {},
      "uniqueConstraints": {},
      "policies": {},
      "checkConstraints": {},
      "isRLSEnabled": false
    },
    "public.users": {
      "name": "users",
      "schema": "",
      "columns": {
        "id": {
          "name": "id",
          "type": "uuid",
          "primaryKey": true,
          "notNull": true,
          "default": "gen_random_uuid()"
        },
        "email": {
          "name": "email",
          "type": "text",
          "primaryKey": false,
          "notNull": true
        },
        "email_verified": {
          "name": "email_verified",
          "type": "timestamp with time zone",
          "primaryKey": false,
          "notNull": false
        },
        "name": {
          "name": "name",
          "type": "text",
          "primaryKey": false,
          "notNull": false
        },
        "image": {
          "name": "image",
          "type": "text",
          "primaryKey": false,
          "notNull": false
        },
        "role": {
          "name": "role",
          "type": "user_role",
          "typeSchema": "public",
          "primaryKey": false,
          "notNull": true,
          "default": "'reviewer'"
        },
        "status": {
          "name": "status",
          "type": "user_status",
          "typeSchema": "public",
          "primaryKey": false,
          "notNull": true,
          "default": "'invited'"
        },
        "mfa_verified_at": {
          "name": "mfa_verified_at",
          "type": "timestamp with time zone",
          "primaryKey": false,
          "notNull": false
        },
        "created_at": {
          "name": "created_at",
          "type": "timestamp with time zone",
          "primaryKey": false,
          "notNull": true,
          "default": "now()"
        },
        "updated_at": {
          "name": "updated_at",
          "type": "timestamp with time zone",
          "primaryKey": false,
          "notNull": true,
          "default": "now()"
        }
      },
      "indexes": {},
      "foreignKeys": {},
      "compositePrimaryKeys": {},
      "uniqueConstraints": {
        "users_email_unique": {
          "name": "users_email_unique",
          "nullsNotDistinct": false,
          "columns": [
            "email"
          ]
        }
      },
      "policies": {},
      "checkConstraints": {},
      "isRLSEnabled": false
    },
    "public.verification_tokens": {
      "name": "verification_tokens",
      "schema": "",
      "columns": {
        "identifier": {
          "name": "identifier",
          "type": "text",
          "primaryKey": false,
          "notNull": true
        },
        "token": {
          "name": "token",
          "type": "text",
          "primaryKey": false,
          "notNull": true
        },
        "expires": {
          "name": "expires",
          "type": "timestamp with time zone",
          "primaryKey": false,
          "notNull": true
        }
      },
      "indexes": {},
      "foreignKeys": {},
      "compositePrimaryKeys": {
        "verification_tokens_identifier_token_pk": {
          "name": "verification_tokens_identifier_token_pk",
          "columns": [
            "identifier",
            "token"
          ]
        }
      },
      "uniqueConstraints": {},
      "policies": {},
      "checkConstraints": {},
      "isRLSEnabled": false
    }
  },
  "enums": {
    "public.asset_kind": {
      "name": "asset_kind",
      "schema": "public",
      "values": [
        "photo",
        "floor_plan",
        "logo",
        "document"
      ]
    },
    "public.asset_status": {
      "name": "asset_status",
      "schema": "public",
      "values": [
        "active",
        "needs_permission",
        "removed"
      ]
    },
    "public.building_status": {
      "name": "building_status",
      "schema": "public",
      "values": [
        "draft",
        "staged",
        "published",
        "archived"
      ]
    },
    "public.floor_plan_type": {
      "name": "floor_plan_type",
      "schema": "public",
      "values": [
        "pdf",
        "image",
        "embed"
      ]
    },
    "public.job_stage": {
      "name": "job_stage",
      "schema": "public",
      "values": [
        "intake",
        "crawl",
        "classify",
        "extract",
        "asset_harvest",
        "validate",
        "review",
        "monitor"
      ]
    },
    "public.job_status": {
      "name": "job_status",
      "schema": "public",
      "values": [
        "queued",
        "running",
        "blocked",
        "ready_for_review",
        "failed",
        "completed"
      ]
    },
    "public.license_basis": {
      "name": "license_basis",
      "schema": "public",
      "values": [
        "official_public",
        "owner_submitted",
        "licensed",
        "needs_permission"
      ]
    },
    "public.link_kind": {
      "name": "link_kind",
      "schema": "public",
      "values": [
        "official_site",
        "leasing_page",
        "availability",
        "contact"
      ]
    },
    "public.review_status": {
      "name": "review_status",
      "schema": "public",
      "values": [
        "open",
        "in_progress",
        "approved",
        "rejected"
      ]
    },
    "public.review_type": {
      "name": "review_type",
      "schema": "public",
      "values": [
        "new",
        "recrawl_diff",
        "correction",
        "flagged"
      ]
    },
    "public.submission_status": {
      "name": "submission_status",
      "schema": "public",
      "values": [
        "received",
        "queued",
        "duplicate",
        "blocked",
        "completed"
      ]
    },
    "public.task_kind": {
      "name": "task_kind",
      "schema": "public",
      "values": [
        "floor_plans",
        "photos",
        "unit_mix",
        "leasing_link",
        "other"
      ]
    },
    "public.task_status": {
      "name": "task_status",
      "schema": "public",
      "values": [
        "backlog",
        "researching",
        "blocked",
        "ready_for_review",
        "done"
      ]
    },
    "public.user_role": {
      "name": "user_role",
      "schema": "public",
      "values": [
        "admin",
        "reviewer",
        "owner"
      ]
    },
    "public.user_status": {
      "name": "user_status",
      "schema": "public",
      "values": [
        "invited",
        "active",
        "suspended"
      ]
    },
    "public.verification_status": {
      "name": "verification_status",
      "schema": "public",
      "values": [
        "unverified",
        "verified",
        "dead",
        "blocked"
      ]
    }
  },
  "schemas": {},
  "sequences": {},
  "roles": {},
  "policies": {},
  "views": {},
  "_meta": {
    "columns": {},
    "schemas": {},
    "tables": {}
  }
}